mlgauge/VERSION
mlgauge/__init__.py
mlgauge/analysis.py
mlgauge/method.py
mlgauge/utils.py
mlgauge-0.3.3.dist-info/LICENSE
mlgauge-0.3.3.dist-info/METADATA
mlgauge-0.3.3.dist-info/WHEEL
mlgauge-0.3.3.dist-info/top_level.txt
mlgauge-0.3.3.dist-info/RECORD
