Metadata-Version: 2.1
Name: mlgauge
Version: 0.3.3
Summary: Library to compare machine learning methods across datasets
Home-page: https://github.com/SuryaThiru/mlgauge
Author: Surya Krishnamurthy
License: License :: OSI Approved :: MIT License
Keywords: machine learning,benchmark,pmlb
Platform: UNKNOWN
Classifier: Intended Audience :: Science/Research
Classifier: Intended Audience :: Education
Classifier: Topic :: Scientific/Engineering
Classifier: Topic :: Utilities
Requires-Dist: openml (>=0.11.0)
Requires-Dist: pmlb (>=1.0)
Requires-Dist: pandas (>=1.0.3)
Requires-Dist: scikit-learn (>=0.22.2)
Requires-Dist: joblib (>=0.17.0)
Requires-Dist: seaborn (>=0.11)
Requires-Dist: xarray (>=0.16.1)
Requires-Dist: tqdm (>=4.48.1)
